ndeleh_fba/__init__.py
ndeleh_fba/auto_edges.py
ndeleh_fba/fishbone.py
ndeleh_fba/fishbone_v2.py
ndeleh_fba/graph.py
ndeleh_fba/ribs.py
ndeleh_fba/schemas.py
ndeleh_fba/spine.py
ndeleh_fba/spine_v2.py
ndeleh_fba/visualize_microspine.py
ndeleh_fba/api/__init__.py
ndeleh_fba/api/auth.py
ndeleh_fba/api/fishbone_v2_api.py
ndeleh_fba/api/industrial_endpoints.py
ndeleh_fba/api/schemas.py
ndeleh_fba/api/server.py
ndeleh_fba/api/torque_api.py
ndeleh_fba/api/torque_reasoning_api.py
ndeleh_fba/cli/__init__.py
ndeleh_fba/cli/fba_cli.py
ndeleh_fba/industrial/__init__.py
ndeleh_fba/industrial/forklift_logic.py
ndeleh_fba/industrial/industrial_logic.py
ndeleh_fba/industrial/line_logic.py
ndeleh_fba/industrial/reasoning_report.py
ndeleh_fba/industrial/torque.py
ndeleh_fba/industrial/torque_to_graph.py
ndeleh_fba/visualize/__init__.py
ndeleh_fba/visualize/plot.py
ndeleh_fba-1.1.0.dist-info/licenses/LICENSE
ndeleh_fba-1.1.0.dist-info/METADATA
ndeleh_fba-1.1.0.dist-info/WHEEL
ndeleh_fba-1.1.0.dist-info/top_level.txt
ndeleh_fba-1.1.0.dist-info/RECORD
