Metadata-Version: 2.4
Name: ndeleh-fba
Version: 1.1.0
Summary: N-FBA V2: A modern fishbone root-cause reasoning engine for industrial diagnostics.
Author: Ndeleh
License: Apache-2.0
Project-URL: Homepage, https://github.com/NDELEH/ndeleh-fba
Project-URL: Repository, https://github.com/NDELEH/ndeleh-fba
Project-URL: Issues, https://github.com/NDELEH/ndeleh-fba/issues
Project-URL: Documentation, https://github.com/NDELEH/ndeleh-fba
Keywords: fishbone,root-cause,diagnostics,industrial,quality,graphs,manufacturing,AI,N-FBA
Requires-Python: >=3.9
License-File: LICENSE
Requires-Dist: fastapi>=0.111
Requires-Dist: uvicorn>=0.29
Dynamic: license-file
